ctypes_helper/__init__.py
ctypes_helper/_version.py
ctypes_helper/ast_parser.py
ctypes_helper/cdecl_parser.py
ctypes_helper/clang_helper.py
ctypes_helper/ctypes_helper.py
ctypes_helper-0.2.1.dist-info/METADATA
ctypes_helper-0.2.1.dist-info/WHEEL
ctypes_helper-0.2.1.dist-info/RECORD
